acdc.py
acdc-0.1.1.dist-info/LICENSE
acdc-0.1.1.dist-info/WHEEL
acdc-0.1.1.dist-info/METADATA
acdc-0.1.1.dist-info/RECORD
