Metadata-Version: 2.1
Name: acdc
Version: 0.1.1
Summary: Wanna-be fast string search
Home-page: https://git.sr.ht/~amirouche/python-acdc
License: MIT
Author: Amirouche
Author-email: amirouche@hyper.dev
Requires-Python: >=3.7,<4.0
Classifier: License :: OSI Approved :: MIT License
Classifier: Programming Language :: Python :: 3
Classifier: Programming Language :: Python :: 3.7
Classifier: Programming Language :: Python :: 3.8
Classifier: Programming Language :: Python :: 3.9
Project-URL: Repository, https://git.sr.ht/~amirouche/python-acdc
